takeoff_sdk/__init__.py
takeoff_sdk/main.py
takeoff_sdk/sdk/__init__.py
takeoff_sdk/sdk/schema.py
takeoff_sdk/sdk/takeoff.py
takeoff_sdk/sdk/utils.py
takeoff_sdk-0.3.3.dist-info/METADATA
takeoff_sdk-0.3.3.dist-info/WHEEL
takeoff_sdk-0.3.3.dist-info/entry_points.txt
takeoff_sdk-0.3.3.dist-info/top_level.txt
takeoff_sdk-0.3.3.dist-info/RECORD
