Metadata-Version: 2.1
Name: takeoff_sdk
Version: 0.3.3
Summary: Takeoff SDK package is a python sdk that provides a simple interface to interact with Takeoff
Author-email: TitanML <hello@titanml.co>
Requires-Dist: pydantic ==2.5.1
Requires-Dist: pydantic-settings ==2.1.0
Requires-Dist: loguru ==0.6.0
Requires-Dist: docker ==7.0.0
Requires-Dist: typer ==0.9.0
